{
  "18:41:12-bravo": {
    "arena_id": 4975944598256818,
    "cluster_id": 4221,
    "finished_at": "2022-03-17T18:41:12+00:00",
    "id": 5887706,
    "map": {
      "name": "Hotspot"
    },
    "map_id": 9,
    "realm": "eu",
    "season_number": 16,
    "teams": [
      {
        "clan_id": 500202767,
        "division": 1,
        "id": 11705742,
        "claninfo": {
          "id": 11705742,
          "color": "#e3d6a0",
          "members_count": 36,
          "name": "Horde of Eccentrics",
          "tag": "H-O-E",
          "disbanded": false,
          "realm": "eu",
          "hex_color": "#e3d6a0"
        },
        "players": [
          {
            "nickname": "Phantom_1511",
            "ship": {
              "level": 10,
              "name": "Shimakaze"
            },
            "vehicle_id": 4282267344,
            "clan_id": 500202767,
            "survived": false,
            "result_id": 11705742,
            "name": "Phantom_1511",
            "spa_id": 551700897
          },
          {
            "nickname": "Yuu5Eleven",
            "ship": {
              "level": 10,
              "name": "Puerto Rico"
            },
            "vehicle_id": 3655251952,
            "clan_id": 500202767,
            "survived": false,
            "result_id": 11705742,
            "name": "Yuu5Eleven",
            "spa_id": 551905283
          },
          {
            "nickname": "Jelisarius",
            "ship": {
              "level": 10,
              "name": "Ohio"
            },
            "vehicle_id": 3760142320,
            "clan_id": 500202767,
            "survived": false,
            "result_id": 11705742,
            "name": "Jelisarius",
            "spa_id": 566641028
          },
          {
            "nickname": "Janiksenkapala",
            "ship": {
              "level": 10,
              "name": "Napoli"
            },
            "vehicle_id": 3760109296,
            "clan_id": 500202767,
            "survived": true,
            "result_id": 11705742,
            "name": "Janiksenkapala",
            "spa_id": 521947080
          },
          {
            "nickname": "PantherGraph",
            "ship": {
              "level": 10,
              "name": "Montana"
            },
            "vehicle_id": 4277090288,
            "clan_id": 500202767,
            "survived": true,
            "result_id": 11705742,
            "name": "PantherGraph",
            "spa_id": 527886188
          },
          {
            "nickname": "Shadypleb",
            "ship": {
              "level": 10,
              "name": "Småland"
            },
            "vehicle_id": 3655218480,
            "clan_id": 500202767,
            "survived": true,
            "result_id": 11705742,
            "name": "Shadypleb",
            "spa_id": 500575636
          },
          {
            "nickname": "jayceedee",
            "ship": {
              "level": 10,
              "name": "Moskva"
            },
            "vehicle_id": 4179539408,
            "clan_id": 500202767,
            "survived": true,
            "result_id": 11705742,
            "name": "jayceedee",
            "spa_id": 556002838
          }
        ],
        "rating_delta": -18,
        "league": 2,
        "division_rating": 26,
        "team_number": 2,
        "stage": null,
        "result": "defeat"
      },
      {
        "clan_id": 500189446,
        "division": 1,
        "id": 11705741,
        "claninfo": {
          "id": 11705741,
          "color": "#e3d6a0",
          "members_count": 27,
          "name": "Let's start the show!",
          "tag": "SH0W",
          "disbanded": false,
          "realm": "eu",
          "hex_color": "#e3d6a0"
        },
        "players": [
          {
            "nickname": "DevcuBe",
            "ship": {
              "level": 10,
              "name": "Ragnar"
            },
            "vehicle_id": 3550360880,
            "clan_id": 500189446,
            "survived": false,
            "result_id": 11705741,
            "name": "DevcuBe",
            "spa_id": 530017602
          },
          {
            "nickname": "_Olszewa_",
            "ship": {
              "level": 10,
              "name": "Kremlin"
            },
            "vehicle_id": 4179572176,
            "clan_id": 500189446,
            "survived": false,
            "result_id": 11705741,
            "name": "_Olszewa_",
            "spa_id": 517438518
          },
          {
            "nickname": "Petrusx_",
            "ship": {
              "level": 10,
              "name": "Napoli"
            },
            "vehicle_id": 3760109296,
            "clan_id": 500189446,
            "survived": true,
            "result_id": 11705741,
            "name": "Petrusx_",
            "spa_id": 516600999
          },
          {
            "nickname": "tomislawt",
            "ship": {
              "level": 10,
              "name": "Moskva"
            },
            "vehicle_id": 4179539408,
            "clan_id": 500189446,
            "survived": true,
            "result_id": 11705741,
            "name": "tomislawt",
            "spa_id": 504855253
          },
          {
            "nickname": "Cyraxinainen",
            "ship": {
              "level": 10,
              "name": "Ohio"
            },
            "vehicle_id": 3760142320,
            "clan_id": 500189446,
            "survived": true,
            "result_id": 11705741,
            "name": "Cyraxinainen",
            "spa_id": 510646391
          },
          {
            "nickname": "Sowster",
            "ship": {
              "level": 10,
              "name": "Des Moines"
            },
            "vehicle_id": 4273911792,
            "clan_id": 500189446,
            "survived": true,
            "result_id": 11705741,
            "name": "Sowster",
            "spa_id": 534111188
          },
          {
            "nickname": "BartiM4",
            "ship": {
              "level": 10,
              "name": "Småland"
            },
            "vehicle_id": 3655218480,
            "clan_id": 500189446,
            "survived": true,
            "result_id": 11705741,
            "name": "BartiM4",
            "spa_id": 514038906
          }
        ],
        "rating_delta": 21,
        "league": 2,
        "division_rating": 64,
        "team_number": 1,
        "stage": null,
        "result": "victory"
      }
    ]
  },
  "19:01:08-bravo": {
    "arena_id": 5066542638400045,
    "cluster_id": 4224,
    "finished_at": "2022-03-17T19:01:08+00:00",
    "id": 5887993,
    "map": {
      "name": "Crash Zone Alpha"
    },
    "map_id": 32,
    "realm": "eu",
    "season_number": 16,
    "teams": [
      {
        "clan_id": 500202767,
        "division": 1,
        "id": 11706316,
        "claninfo": {
          "id": 11706316,
          "color": "#e3d6a0",
          "members_count": 36,
          "name": "Horde of Eccentrics",
          "tag": "H-O-E",
          "disbanded": false,
          "realm": "eu",
          "hex_color": "#e3d6a0"
        },
        "players": [
          {
            "nickname": "Jelisarius",
            "ship": {
              "level": 10,
              "name": "Ohio"
            },
            "vehicle_id": 3760142320,
            "clan_id": 500202767,
            "survived": false,
            "result_id": 11706316,
            "name": "Jelisarius",
            "spa_id": 566641028
          },
          {
            "nickname": "jayceedee",
            "ship": {
              "level": 10,
              "name": "Moskva"
            },
            "vehicle_id": 4179539408,
            "clan_id": 500202767,
            "survived": true,
            "result_id": 11706316,
            "name": "jayceedee",
            "spa_id": 556002838
          },
          {
            "nickname": "Janiksenkapala",
            "ship": {
              "level": 10,
              "name": "Napoli"
            },
            "vehicle_id": 3760109296,
            "clan_id": 500202767,
            "survived": true,
            "result_id": 11706316,
            "name": "Janiksenkapala",
            "spa_id": 521947080
          },
          {
            "nickname": "PantherGraph",
            "ship": {
              "level": 10,
              "name": "Montana"
            },
            "vehicle_id": 4277090288,
            "clan_id": 500202767,
            "survived": false,
            "result_id": 11706316,
            "name": "PantherGraph",
            "spa_id": 527886188
          },
          {
            "nickname": "Phantom_1511",
            "ship": {
              "level": 10,
              "name": "Shimakaze"
            },
            "vehicle_id": 4282267344,
            "clan_id": 500202767,
            "survived": true,
            "result_id": 11706316,
            "name": "Phantom_1511",
            "spa_id": 551700897
          },
          {
            "nickname": "Yuu5Eleven",
            "ship": {
              "level": 10,
              "name": "Puerto Rico"
            },
            "vehicle_id": 3655251952,
            "clan_id": 500202767,
            "survived": true,
            "result_id": 11706316,
            "name": "Yuu5Eleven",
            "spa_id": 551905283
          },
          {
            "nickname": "Shadypleb",
            "ship": {
              "level": 10,
              "name": "Småland"
            },
            "vehicle_id": 3655218480,
            "clan_id": 500202767,
            "survived": true,
            "result_id": 11706316,
            "name": "Shadypleb",
            "spa_id": 500575636
          }
        ],
        "rating_delta": 22,
        "league": 2,
        "division_rating": 48,
        "team_number": 2,
        "stage": null,
        "result": "victory"
      },
      {
        "clan_id": 500140774,
        "division": 2,
        "id": 11706315,
        "claninfo": {
          "id": 11706315,
          "color": "#e3d6a0",
          "members_count": 29,
          "name": "At Ocean's End",
          "tag": "OE",
          "disbanded": false,
          "realm": "eu",
          "hex_color": "#e3d6a0"
        },
        "players": [
          {
            "nickname": "rocketmaster_2016",
            "ship": {
              "level": 10,
              "name": "Småland"
            },
            "vehicle_id": 3655218480,
            "clan_id": 500140774,
            "survived": true,
            "result_id": 11706315,
            "name": "rocketmaster_2016",
            "spa_id": 541002945
          },
          {
            "nickname": "Fa_Bu_1",
            "ship": {
              "level": 10,
              "name": "Goliath"
            },
            "vehicle_id": 4074682320,
            "clan_id": 500140774,
            "survived": false,
            "result_id": 11706315,
            "name": "Fa_Bu_1",
            "spa_id": 522729251
          },
          {
            "nickname": "Danders4",
            "ship": {
              "level": 10,
              "name": "Ohio"
            },
            "vehicle_id": 3760142320,
            "clan_id": 500140774,
            "survived": false,
            "result_id": 11706315,
            "name": "Danders4",
            "spa_id": 542566849
          },
          {
            "nickname": "hugo54656_1",
            "ship": {
              "level": 10,
              "name": "Moskva"
            },
            "vehicle_id": 4179539408,
            "clan_id": 500140774,
            "survived": false,
            "result_id": 11706315,
            "name": "hugo54656_1",
            "spa_id": 569331433
          },
          {
            "nickname": "Leadersocke",
            "ship": {
              "level": 10,
              "name": "Napoli"
            },
            "vehicle_id": 3760109296,
            "clan_id": 500140774,
            "survived": true,
            "result_id": 11706315,
            "name": "Leadersocke",
            "spa_id": 530046607
          },
          {
            "nickname": "BBsBeautyPalace",
            "ship": {
              "level": 10,
              "name": "Kremlin"
            },
            "vehicle_id": 4179572176,
            "clan_id": 500140774,
            "survived": true,
            "result_id": 11706315,
            "name": "BBsBeautyPalace",
            "spa_id": 503586515
          },
          {
            "nickname": "c_obvious",
            "ship": {
              "level": 10,
              "name": "Ragnar"
            },
            "vehicle_id": 3550360880,
            "clan_id": 500140774,
            "survived": false,
            "result_id": 11706315,
            "name": "c_obvious",
            "spa_id": 567706531
          }
        ],
        "rating_delta": -18,
        "league": 2,
        "division_rating": 4,
        "team_number": 1,
        "stage": null,
        "result": "defeat"
      }
    ]
  },
  "19:18:53-bravo": {
    "arena_id": 5098299626587589,
    "cluster_id": 4221,
    "finished_at": "2022-03-17T19:18:53+00:00",
    "id": 5888268,
    "map": {
      "name": "Land of Fire"
    },
    "map_id": 14,
    "realm": "eu",
    "season_number": 16,
    "teams": [
      {
        "clan_id": 500202767,
        "division": 1,
        "id": 11706866,
        "claninfo": {
          "id": 11706866,
          "color": "#e3d6a0",
          "members_count": 36,
          "name": "Horde of Eccentrics",
          "tag": "H-O-E",
          "disbanded": false,
          "realm": "eu",
          "hex_color": "#e3d6a0"
        },
        "players": [
          {
            "nickname": "Phantom_1511",
            "ship": {
              "level": 10,
              "name": "Shimakaze"
            },
            "vehicle_id": 4282267344,
            "clan_id": 500202767,
            "survived": false,
            "result_id": 11706866,
            "name": "Phantom_1511",
            "spa_id": 551700897
          },
          {
            "nickname": "Yuu5Eleven",
            "ship": {
              "level": 10,
              "name": "Puerto Rico"
            },
            "vehicle_id": 3655251952,
            "clan_id": 500202767,
            "survived": false,
            "result_id": 11706866,
            "name": "Yuu5Eleven",
            "spa_id": 551905283
          },
          {
            "nickname": "Jelisarius",
            "ship": {
              "level": 10,
              "name": "Ohio"
            },
            "vehicle_id": 3760142320,
            "clan_id": 500202767,
            "survived": true,
            "result_id": 11706866,
            "name": "Jelisarius",
            "spa_id": 566641028
          },
          {
            "nickname": "Janiksenkapala",
            "ship": {
              "level": 10,
              "name": "Napoli"
            },
            "vehicle_id": 3760109296,
            "clan_id": 500202767,
            "survived": true,
            "result_id": 11706866,
            "name": "Janiksenkapala",
            "spa_id": 521947080
          },
          {
            "nickname": "PantherGraph",
            "ship": {
              "level": 10,
              "name": "Montana"
            },
            "vehicle_id": 4277090288,
            "clan_id": 500202767,
            "survived": false,
            "result_id": 11706866,
            "name": "PantherGraph",
            "spa_id": 527886188
          },
          {
            "nickname": "Shadypleb",
            "ship": {
              "level": 10,
              "name": "Småland"
            },
            "vehicle_id": 3655218480,
            "clan_id": 500202767,
            "survived": false,
            "result_id": 11706866,
            "name": "Shadypleb",
            "spa_id": 500575636
          },
          {
            "nickname": "jayceedee",
            "ship": {
              "level": 10,
              "name": "Moskva"
            },
            "vehicle_id": 4179539408,
            "clan_id": 500202767,
            "survived": true,
            "result_id": 11706866,
            "name": "jayceedee",
            "spa_id": 556002838
          }
        ],
        "rating_delta": -18,
        "league": 2,
        "division_rating": 30,
        "team_number": 2,
        "stage": null,
        "result": "defeat"
      },
      {
        "clan_id": 500143673,
        "division": 3,
        "id": 11706865,
        "claninfo": {
          "id": 11706865,
          "color": "#bee7bd",
          "members_count": 36,
          "name": "Geil was?!?",
          "tag": "GWHAT",
          "disbanded": false,
          "realm": "eu",
          "hex_color": "#bee7bd"
        },
        "players": [
          {
            "nickname": "FurorGermanicus_",
            "ship": {
              "level": 10,
              "name": "Napoli"
            },
            "vehicle_id": 3760109296,
            "clan_id": 500143673,
            "survived": false,
            "result_id": 11706865,
            "name": "FurorGermanicus_",
            "spa_id": 529838177
          },
          {
            "nickname": "Horst_Koehler",
            "ship": {
              "level": 10,
              "name": "Kremlin"
            },
            "vehicle_id": 4179572176,
            "clan_id": 500143673,
            "survived": true,
            "result_id": 11706865,
            "name": "Horst_Koehler",
            "spa_id": 529345132
          },
          {
            "nickname": "Thomyatberlin",
            "ship": {
              "level": 10,
              "name": "Schlieffen"
            },
            "vehicle_id": 4074714928,
            "clan_id": 500143673,
            "survived": true,
            "result_id": 11706865,
            "name": "Thomyatberlin",
            "spa_id": 529134351
          },
          {
            "nickname": "Sowl_Kautschuk",
            "ship": {
              "level": 10,
              "name": "Moskva"
            },
            "vehicle_id": 4179539408,
            "clan_id": 500143673,
            "survived": true,
            "result_id": 11706865,
            "name": "Sowl_Kautschuk",
            "spa_id": 539613808
          },
          {
            "nickname": "TOXIC_DD_MAIN",
            "ship": {
              "level": 10,
              "name": "Småland"
            },
            "vehicle_id": 3655218480,
            "clan_id": 500143673,
            "survived": false,
            "result_id": 11706865,
            "name": "TOXIC_DD_MAIN",
            "spa_id": 549720849
          },
          {
            "nickname": "_S0ME0NE",
            "ship": {
              "level": 10,
              "name": "Des Moines"
            },
            "vehicle_id": 4273911792,
            "clan_id": 500143673,
            "survived": false,
            "result_id": 11706865,
            "name": "_S0ME0NE",
            "spa_id": 542072888
          },
          {
            "nickname": "Marc_Anton",
            "ship": {
              "level": 10,
              "name": "Somers"
            },
            "vehicle_id": 3760076784,
            "clan_id": 500143673,
            "survived": true,
            "result_id": 11706865,
            "name": "Marc_Anton",
            "spa_id": 544463919
          }
        ],
        "rating_delta": 20,
        "league": 1,
        "division_rating": 41,
        "team_number": 1,
        "stage": null,
        "result": "victory"
      }
    ]
  },
  "19:37:21-bravo": {
    "arena_id": 4561484549163824,
    "cluster_id": 4224,
    "finished_at": "2022-03-17T19:37:21+00:00",
    "id": 5888600,
    "map": {
      "name": "Islands of Ice"
    },
    "map_id": 11,
    "realm": "eu",
    "season_number": 16,
    "teams": [
      {
        "clan_id": 500202767,
        "division": 1,
        "id": 11707530,
        "claninfo": {
          "id": 11707530,
          "color": "#e3d6a0",
          "members_count": 36,
          "name": "Horde of Eccentrics",
          "tag": "H-O-E",
          "disbanded": false,
          "realm": "eu",
          "hex_color": "#e3d6a0"
        },
        "players": [
          {
            "nickname": "Phantom_1511",
            "ship": {
              "level": 10,
              "name": "Shimakaze"
            },
            "vehicle_id": 4282267344,
            "clan_id": 500202767,
            "survived": false,
            "result_id": 11707530,
            "name": "Phantom_1511",
            "spa_id": 551700897
          },
          {
            "nickname": "Yuu5Eleven",
            "ship": {
              "level": 10,
              "name": "Puerto Rico"
            },
            "vehicle_id": 3655251952,
            "clan_id": 500202767,
            "survived": false,
            "result_id": 11707530,
            "name": "Yuu5Eleven",
            "spa_id": 551905283
          },
          {
            "nickname": "PantherGraph",
            "ship": {
              "level": 10,
              "name": "Montana"
            },
            "vehicle_id": 4277090288,
            "clan_id": 500202767,
            "survived": false,
            "result_id": 11707530,
            "name": "PantherGraph",
            "spa_id": 527886188
          },
          {
            "nickname": "Shadypleb",
            "ship": {
              "level": 10,
              "name": "Småland"
            },
            "vehicle_id": 3655218480,
            "clan_id": 500202767,
            "survived": false,
            "result_id": 11707530,
            "name": "Shadypleb",
            "spa_id": 500575636
          },
          {
            "nickname": "jayceedee",
            "ship": {
              "level": 10,
              "name": "Moskva"
            },
            "vehicle_id": 4179539408,
            "clan_id": 500202767,
            "survived": false,
            "result_id": 11707530,
            "name": "jayceedee",
            "spa_id": 556002838
          },
          {
            "nickname": "_Carlo96_",
            "ship": {
              "level": 10,
              "name": "Ohio"
            },
            "vehicle_id": 3760142320,
            "clan_id": 500202767,
            "survived": false,
            "result_id": 11707530,
            "name": "_Carlo96_",
            "spa_id": 555682744
          },
          {
            "nickname": "Ghesthar",
            "ship": {
              "level": 10,
              "name": "Napoli"
            },
            "vehicle_id": 3760109296,
            "clan_id": 500202767,
            "survived": false,
            "result_id": 11707530,
            "name": "Ghesthar",
            "spa_id": 500031647
          }
        ],
        "rating_delta": -21,
        "league": 2,
        "division_rating": 9,
        "team_number": 2,
        "stage": null,
        "result": "defeat"
      },
      {
        "clan_id": 500140048,
        "division": 2,
        "id": 11707529,
        "claninfo": {
          "id": 11707529,
          "color": "#e3d6a0",
          "members_count": 38,
          "name": "Fun Police",
          "tag": "NOFUN",
          "disbanded": false,
          "realm": "eu",
          "hex_color": "#e3d6a0"
        },
        "players": [
          {
            "nickname": "Admiral_Jellicoe",
            "ship": {
              "level": 10,
              "name": "Ohio"
            },
            "vehicle_id": 3760142320,
            "clan_id": 500140048,
            "survived": true,
            "result_id": 11707529,
            "name": "Admiral_Jellicoe",
            "spa_id": 528781314
          },
          {
            "nickname": "Tracinta",
            "ship": {
              "level": 10,
              "name": "Napoli"
            },
            "vehicle_id": 3760109296,
            "clan_id": 500140048,
            "survived": true,
            "result_id": 11707529,
            "name": "Tracinta",
            "spa_id": 517301253
          },
          {
            "nickname": "IvanTheTerrrible",
            "ship": {
              "level": 10,
              "name": "Conqueror"
            },
            "vehicle_id": 4179572688,
            "clan_id": 500140048,
            "survived": true,
            "result_id": 11707529,
            "name": "IvanTheTerrrible",
            "spa_id": 521295304
          },
          {
            "nickname": "Bachiri22",
            "ship": {
              "level": 10,
              "name": "Ragnar"
            },
            "vehicle_id": 3550360880,
            "clan_id": 500140048,
            "survived": false,
            "result_id": 11707529,
            "name": "Bachiri22",
            "spa_id": 530848106
          },
          {
            "nickname": "Snorky_the_goblin",
            "ship": {
              "level": 10,
              "name": "Stalingrad"
            },
            "vehicle_id": 3760109008,
            "clan_id": 500140048,
            "survived": false,
            "result_id": 11707529,
            "name": "Snorky_the_goblin",
            "spa_id": 500153005
          },
          {
            "nickname": "YouCanCallMeSusan",
            "ship": {
              "level": 10,
              "name": "Småland"
            },
            "vehicle_id": 3655218480,
            "clan_id": 500140048,
            "survived": false,
            "result_id": 11707529,
            "name": "YouCanCallMeSusan",
            "spa_id": 522553421
          },
          {
            "nickname": "ImperialByte",
            "ship": {
              "level": 10,
              "name": "Des Moines"
            },
            "vehicle_id": 4273911792,
            "clan_id": 500140048,
            "survived": true,
            "result_id": 11707529,
            "name": "ImperialByte",
            "spa_id": 534997949
          }
        ],
        "rating_delta": 25,
        "league": 2,
        "division_rating": 59,
        "team_number": 2,
        "stage": null,
        "result": "victory"
      }
    ]
  },
  "19:49:41-bravo": {
    "arena_id": 4724633176870464,
    "cluster_id": 4221,
    "finished_at": "2022-03-17T19:49:41+00:00",
    "id": 5888827,
    "map": {
      "name": "Shards"
    },
    "map_id": 15,
    "realm": "eu",
    "season_number": 16,
    "teams": [
      {
        "clan_id": 500202767,
        "division": 1,
        "id": 11707984,
        "claninfo": {
          "id": 11707984,
          "color": "#e3d6a0",
          "members_count": 36,
          "name": "Horde of Eccentrics",
          "tag": "H-O-E",
          "disbanded": false,
          "realm": "eu",
          "hex_color": "#e3d6a0"
        },
        "players": [
          {
            "nickname": "Phantom_1511",
            "ship": {
              "level": 10,
              "name": "Shimakaze"
            },
            "vehicle_id": 4282267344,
            "clan_id": 500202767,
            "survived": true,
            "result_id": 11707984,
            "name": "Phantom_1511",
            "spa_id": 551700897
          },
          {
            "nickname": "Yuu5Eleven",
            "ship": {
              "level": 10,
              "name": "Puerto Rico"
            },
            "vehicle_id": 3655251952,
            "clan_id": 500202767,
            "survived": true,
            "result_id": 11707984,
            "name": "Yuu5Eleven",
            "spa_id": 551905283
          },
          {
            "nickname": "PantherGraph",
            "ship": {
              "level": 10,
              "name": "Montana"
            },
            "vehicle_id": 4277090288,
            "clan_id": 500202767,
            "survived": true,
            "result_id": 11707984,
            "name": "PantherGraph",
            "spa_id": 527886188
          },
          {
            "nickname": "Shadypleb",
            "ship": {
              "level": 10,
              "name": "Småland"
            },
            "vehicle_id": 3655218480,
            "clan_id": 500202767,
            "survived": true,
            "result_id": 11707984,
            "name": "Shadypleb",
            "spa_id": 500575636
          },
          {
            "nickname": "jayceedee",
            "ship": {
              "level": 10,
              "name": "Moskva"
            },
            "vehicle_id": 4179539408,
            "clan_id": 500202767,
            "survived": true,
            "result_id": 11707984,
            "name": "jayceedee",
            "spa_id": 556002838
          },
          {
            "nickname": "_Carlo96_",
            "ship": {
              "level": 10,
              "name": "Ohio"
            },
            "vehicle_id": 3760142320,
            "clan_id": 500202767,
            "survived": true,
            "result_id": 11707984,
            "name": "_Carlo96_",
            "spa_id": 555682744
          },
          {
            "nickname": "Ghesthar",
            "ship": {
              "level": 10,
              "name": "Napoli"
            },
            "vehicle_id": 3760109296,
            "clan_id": 500202767,
            "survived": true,
            "result_id": 11707984,
            "name": "Ghesthar",
            "spa_id": 500031647
          }
        ],
        "rating_delta": 20,
        "league": 2,
        "division_rating": 29,
        "team_number": 2,
        "stage": null,
        "result": "victory"
      },
      {
        "clan_id": 500167765,
        "division": 2,
        "id": 11707983,
        "claninfo": {
          "id": 11707983,
          "color": "#e3d6a0",
          "members_count": 31,
          "name": "RATAS MOJADAS (ESPAÑA)",
          "tag": "RATAS",
          "disbanded": false,
          "realm": "eu",
          "hex_color": "#e3d6a0"
        },
        "players": [
          {
            "nickname": "CANTABRO1997",
            "ship": {
              "level": 10,
              "name": "Kremlin"
            },
            "vehicle_id": 4179572176,
            "clan_id": 500167765,
            "survived": false,
            "result_id": 11707983,
            "name": "CANTABRO1997",
            "spa_id": 554615008
          },
          {
            "nickname": "Amenhotep_IV",
            "ship": {
              "level": 10,
              "name": "Småland"
            },
            "vehicle_id": 3655218480,
            "clan_id": 500167765,
            "survived": false,
            "result_id": 11707983,
            "name": "Amenhotep_IV",
            "spa_id": 514237954
          },
          {
            "nickname": "Segaddor",
            "ship": {
              "level": 10,
              "name": "Stalingrad"
            },
            "vehicle_id": 3760109008,
            "clan_id": 500167765,
            "survived": true,
            "result_id": 11707983,
            "name": "Segaddor",
            "spa_id": 556337316
          },
          {
            "nickname": "vixium",
            "ship": {
              "level": 10,
              "name": "Des Moines"
            },
            "vehicle_id": 4273911792,
            "clan_id": 500167765,
            "survived": false,
            "result_id": 11707983,
            "name": "vixium",
            "spa_id": 557515237
          },
          {
            "nickname": "kettepetten",
            "ship": {
              "level": 10,
              "name": "Ohio"
            },
            "vehicle_id": 3760142320,
            "clan_id": 500167765,
            "survived": true,
            "result_id": 11707983,
            "name": "kettepetten",
            "spa_id": 544038933
          },
          {
            "nickname": "Odiel5",
            "ship": {
              "level": 10,
              "name": "Somers"
            },
            "vehicle_id": 3760076784,
            "clan_id": 500167765,
            "survived": true,
            "result_id": 11707983,
            "name": "Odiel5",
            "spa_id": 571325852
          },
          {
            "nickname": "Rowith",
            "ship": {
              "level": 10,
              "name": "Moskva"
            },
            "vehicle_id": 4179539408,
            "clan_id": 500167765,
            "survived": true,
            "result_id": 11707983,
            "name": "Rowith",
            "spa_id": 571340253
          }
        ],
        "rating_delta": -19,
        "league": 2,
        "division_rating": 53,
        "team_number": 1,
        "stage": null,
        "result": "defeat"
      }
    ]
  },
  "20:04:07-bravo": {
    "arena_id": 5205261492130129,
    "cluster_id": 4224,
    "finished_at": "2022-03-17T20:04:07+00:00",
    "id": 5889100,
    "map": {
      "name": "North"
    },
    "map_id": 8,
    "realm": "eu",
    "season_number": 16,
    "teams": [
      {
        "clan_id": 500202767,
        "division": 1,
        "id": 11708530,
        "claninfo": {
          "id": 11708530,
          "color": "#e3d6a0",
          "members_count": 36,
          "name": "Horde of Eccentrics",
          "tag": "H-O-E",
          "disbanded": false,
          "realm": "eu",
          "hex_color": "#e3d6a0"
        },
        "players": [
          {
            "nickname": "Phantom_1511",
            "ship": {
              "level": 10,
              "name": "Shimakaze"
            },
            "vehicle_id": 4282267344,
            "clan_id": 500202767,
            "survived": false,
            "result_id": 11708530,
            "name": "Phantom_1511",
            "spa_id": 551700897
          },
          {
            "nickname": "Yuu5Eleven",
            "ship": {
              "level": 10,
              "name": "Puerto Rico"
            },
            "vehicle_id": 3655251952,
            "clan_id": 500202767,
            "survived": false,
            "result_id": 11708530,
            "name": "Yuu5Eleven",
            "spa_id": 551905283
          },
          {
            "nickname": "PantherGraph",
            "ship": {
              "level": 10,
              "name": "Montana"
            },
            "vehicle_id": 4277090288,
            "clan_id": 500202767,
            "survived": false,
            "result_id": 11708530,
            "name": "PantherGraph",
            "spa_id": 527886188
          },
          {
            "nickname": "Shadypleb",
            "ship": {
              "level": 10,
              "name": "Småland"
            },
            "vehicle_id": 3655218480,
            "clan_id": 500202767,
            "survived": false,
            "result_id": 11708530,
            "name": "Shadypleb",
            "spa_id": 500575636
          },
          {
            "nickname": "jayceedee",
            "ship": {
              "level": 10,
              "name": "Moskva"
            },
            "vehicle_id": 4179539408,
            "clan_id": 500202767,
            "survived": false,
            "result_id": 11708530,
            "name": "jayceedee",
            "spa_id": 556002838
          },
          {
            "nickname": "_Carlo96_",
            "ship": {
              "level": 10,
              "name": "Ohio"
            },
            "vehicle_id": 3760142320,
            "clan_id": 500202767,
            "survived": false,
            "result_id": 11708530,
            "name": "_Carlo96_",
            "spa_id": 555682744
          },
          {
            "nickname": "Ghesthar",
            "ship": {
              "level": 10,
              "name": "Napoli"
            },
            "vehicle_id": 3760109296,
            "clan_id": 500202767,
            "survived": false,
            "result_id": 11708530,
            "name": "Ghesthar",
            "spa_id": 500031647
          }
        ],
        "rating_delta": -19,
        "league": 2,
        "division_rating": 10,
        "team_number": 2,
        "stage": null,
        "result": "defeat"
      },
      {
        "clan_id": 500188874,
        "division": 1,
        "id": 11708529,
        "claninfo": {
          "id": 11708529,
          "color": "#e3d6a0",
          "members_count": 48,
          "name": "Postrzeleni w Cytadele",
          "tag": "P-W-C",
          "disbanded": false,
          "realm": "eu",
          "hex_color": "#e3d6a0"
        },
        "players": [
          {
            "nickname": "DarthReevan",
            "ship": {
              "level": 10,
              "name": "Napoli"
            },
            "vehicle_id": 3760109296,
            "clan_id": 500188874,
            "survived": true,
            "result_id": 11708529,
            "name": "DarthReevan",
            "spa_id": 514226082
          },
          {
            "nickname": "Euzebias",
            "ship": {
              "level": 10,
              "name": "Kremlin"
            },
            "vehicle_id": 4179572176,
            "clan_id": 500188874,
            "survived": true,
            "result_id": 11708529,
            "name": "Euzebias",
            "spa_id": 529271914
          },
          {
            "nickname": "kapitan_Al",
            "ship": {
              "level": 10,
              "name": "Småland"
            },
            "vehicle_id": 3655218480,
            "clan_id": 500188874,
            "survived": true,
            "result_id": 11708529,
            "name": "kapitan_Al",
            "spa_id": 531197774
          },
          {
            "nickname": "tentative_noob",
            "ship": {
              "level": 10,
              "name": "Moskva"
            },
            "vehicle_id": 4179539408,
            "clan_id": 500188874,
            "survived": true,
            "result_id": 11708529,
            "name": "tentative_noob",
            "spa_id": 530774671
          },
          {
            "nickname": "CallMeQuartz",
            "ship": {
              "level": 10,
              "name": "Kléber"
            },
            "vehicle_id": 4179507024,
            "clan_id": 500188874,
            "survived": true,
            "result_id": 11708529,
            "name": "CallMeQuartz",
            "spa_id": 551280729
          },
          {
            "nickname": "VENOM_0514",
            "ship": {
              "level": 10,
              "name": "Ragnar"
            },
            "vehicle_id": 3550360880,
            "clan_id": 500188874,
            "survived": true,
            "result_id": 11708529,
            "name": "VENOM_0514",
            "spa_id": 504838218
          },
          {
            "nickname": "NIEZATAPIALNY_chyba",
            "ship": {
              "level": 10,
              "name": "Ohio"
            },
            "vehicle_id": 3760142320,
            "clan_id": 500188874,
            "survived": false,
            "result_id": 11708529,
            "name": "NIEZATAPIALNY_chyba",
            "spa_id": 550059806
          }
        ],
        "rating_delta": 23,
        "league": 2,
        "division_rating": 2,
        "team_number": 1,
        "stage": null,
        "result": "victory"
      }
    ]
  },
  "20:19:02-bravo": {
    "arena_id": 5890454804731048,
    "cluster_id": 4221,
    "finished_at": "2022-03-17T20:19:02+00:00",
    "id": 5889331,
    "map": {
      "name": "Trident"
    },
    "map_id": 24,
    "realm": "eu",
    "season_number": 16,
    "teams": [
      {
        "clan_id": 500202767,
        "division": 2,
        "id": 11708994,
        "claninfo": {
          "id": 11708994,
          "color": "#e3d6a0",
          "members_count": 36,
          "name": "Horde of Eccentrics",
          "tag": "H-O-E",
          "disbanded": false,
          "realm": "eu",
          "hex_color": "#e3d6a0"
        },
        "players": [
          {
            "nickname": "Yuu5Eleven",
            "ship": {
              "level": 10,
              "name": "Ragnar"
            },
            "vehicle_id": 3550360880,
            "clan_id": 500202767,
            "survived": true,
            "result_id": 11708994,
            "name": "Yuu5Eleven",
            "spa_id": 551905283
          },
          {
            "nickname": "PantherGraph",
            "ship": {
              "level": 10,
              "name": "Montana"
            },
            "vehicle_id": 4277090288,
            "clan_id": 500202767,
            "survived": true,
            "result_id": 11708994,
            "name": "PantherGraph",
            "spa_id": 527886188
          },
          {
            "nickname": "Phantom_1511",
            "ship": {
              "level": 10,
              "name": "Shimakaze"
            },
            "vehicle_id": 4282267344,
            "clan_id": 500202767,
            "survived": false,
            "result_id": 11708994,
            "name": "Phantom_1511",
            "spa_id": 551700897
          },
          {
            "nickname": "Shadypleb",
            "ship": {
              "level": 10,
              "name": "Småland"
            },
            "vehicle_id": 3655218480,
            "clan_id": 500202767,
            "survived": false,
            "result_id": 11708994,
            "name": "Shadypleb",
            "spa_id": 500575636
          },
          {
            "nickname": "jayceedee",
            "ship": {
              "level": 10,
              "name": "Moskva"
            },
            "vehicle_id": 4179539408,
            "clan_id": 500202767,
            "survived": true,
            "result_id": 11708994,
            "name": "jayceedee",
            "spa_id": 556002838
          },
          {
            "nickname": "_Carlo96_",
            "ship": {
              "level": 10,
              "name": "Ohio"
            },
            "vehicle_id": 3760142320,
            "clan_id": 500202767,
            "survived": true,
            "result_id": 11708994,
            "name": "_Carlo96_",
            "spa_id": 555682744
          },
          {
            "nickname": "Ghesthar",
            "ship": {
              "level": 10,
              "name": "Napoli"
            },
            "vehicle_id": 3760109296,
            "clan_id": 500202767,
            "survived": false,
            "result_id": 11708994,
            "name": "Ghesthar",
            "spa_id": 500031647
          }
        ],
        "rating_delta": -19,
        "league": 2,
        "division_rating": 91,
        "team_number": 2,
        "stage": null,
        "result": "defeat"
      },
      {
        "clan_id": 500146159,
        "division": 1,
        "id": 11708991,
        "claninfo": {
          "id": 11708991,
          "color": "#e3d6a0",
          "members_count": 31,
          "name": "Carry Me Again",
          "tag": "CARMA",
          "disbanded": false,
          "realm": "eu",
          "hex_color": "#e3d6a0"
        },
        "players": [
          {
            "nickname": "Mirai02",
            "ship": {
              "level": 10,
              "name": "Schlieffen"
            },
            "vehicle_id": 4074714928,
            "clan_id": 500146159,
            "survived": true,
            "result_id": 11708991,
            "name": "Mirai02",
            "spa_id": 529265761
          },
          {
            "nickname": "Black_1010",
            "ship": {
              "level": 10,
              "name": "Marceau"
            },
            "vehicle_id": 4074649424,
            "clan_id": 500146159,
            "survived": true,
            "result_id": 11708991,
            "name": "Black_1010",
            "spa_id": 538581287
          },
          {
            "nickname": "SturmSuccessor",
            "ship": {
              "level": 10,
              "name": "Kléber"
            },
            "vehicle_id": 4179507024,
            "clan_id": 500146159,
            "survived": true,
            "result_id": 11708991,
            "name": "SturmSuccessor",
            "spa_id": 542848168
          },
          {
            "nickname": "sunbeatz",
            "ship": {
              "level": 10,
              "name": "Napoli"
            },
            "vehicle_id": 3760109296,
            "clan_id": 500146159,
            "survived": false,
            "result_id": 11708991,
            "name": "sunbeatz",
            "spa_id": 500548553
          },
          {
            "nickname": "guennasch",
            "ship": {
              "level": 10,
              "name": "Bourgogne"
            },
            "vehicle_id": 3760142160,
            "clan_id": 500146159,
            "survived": false,
            "result_id": 11708991,
            "name": "guennasch",
            "spa_id": 515582028
          },
          {
            "nickname": "rebel4life",
            "ship": {
              "level": 10,
              "name": "Stalingrad"
            },
            "vehicle_id": 3760109008,
            "clan_id": 500146159,
            "survived": false,
            "result_id": 11708991,
            "name": "rebel4life",
            "spa_id": 523299325
          },
          {
            "nickname": "XxSilencer80xX",
            "ship": {
              "level": 10,
              "name": "Moskva"
            },
            "vehicle_id": 4179539408,
            "clan_id": 500146159,
            "survived": false,
            "result_id": 11708991,
            "name": "XxSilencer80xX",
            "spa_id": 540886494
          }
        ],
        "rating_delta": 22,
        "league": 2,
        "division_rating": 18,
        "team_number": 2,
        "stage": null,
        "result": "victory"
      }
    ]
  },
  "20:33:27-bravo": {
    "arena_id": 5457144144173080,
    "cluster_id": 4221,
    "finished_at": "2022-03-17T20:33:27+00:00",
    "id": 5889558,
    "map": {
      "name": "Crash Zone Alpha"
    },
    "map_id": 32,
    "realm": "eu",
    "season_number": 16,
    "teams": [
      {
        "clan_id": 500202767,
        "division": 1,
        "id": 11709446,
        "claninfo": {
          "id": 11709446,
          "color": "#e3d6a0",
          "members_count": 36,
          "name": "Horde of Eccentrics",
          "tag": "H-O-E",
          "disbanded": false,
          "realm": "eu",
          "hex_color": "#e3d6a0"
        },
        "players": [
          {
            "nickname": "Phantom_1511",
            "ship": {
              "level": 10,
              "name": "Shimakaze"
            },
            "vehicle_id": 4282267344,
            "clan_id": 500202767,
            "survived": true,
            "result_id": 11709446,
            "name": "Phantom_1511",
            "spa_id": 551700897
          },
          {
            "nickname": "Yuu5Eleven",
            "ship": {
              "level": 10,
              "name": "Ragnar"
            },
            "vehicle_id": 3550360880,
            "clan_id": 500202767,
            "survived": false,
            "result_id": 11709446,
            "name": "Yuu5Eleven",
            "spa_id": 551905283
          },
          {
            "nickname": "PantherGraph",
            "ship": {
              "level": 10,
              "name": "Montana"
            },
            "vehicle_id": 4277090288,
            "clan_id": 500202767,
            "survived": true,
            "result_id": 11709446,
            "name": "PantherGraph",
            "spa_id": 527886188
          },
          {
            "nickname": "Shadypleb",
            "ship": {
              "level": 10,
              "name": "Småland"
            },
            "vehicle_id": 3655218480,
            "clan_id": 500202767,
            "survived": true,
            "result_id": 11709446,
            "name": "Shadypleb",
            "spa_id": 500575636
          },
          {
            "nickname": "jayceedee",
            "ship": {
              "level": 10,
              "name": "Moskva"
            },
            "vehicle_id": 4179539408,
            "clan_id": 500202767,
            "survived": true,
            "result_id": 11709446,
            "name": "jayceedee",
            "spa_id": 556002838
          },
          {
            "nickname": "_Carlo96_",
            "ship": {
              "level": 10,
              "name": "Ohio"
            },
            "vehicle_id": 3760142320,
            "clan_id": 500202767,
            "survived": true,
            "result_id": 11709446,
            "name": "_Carlo96_",
            "spa_id": 555682744
          },
          {
            "nickname": "Ghesthar",
            "ship": {
              "level": 10,
              "name": "Napoli"
            },
            "vehicle_id": 3760109296,
            "clan_id": 500202767,
            "survived": true,
            "result_id": 11709446,
            "name": "Ghesthar",
            "spa_id": 500031647
          }
        ],
        "rating_delta": 23,
        "league": 2,
        "division_rating": 14,
        "team_number": 2,
        "stage": null,
        "result": "victory"
      },
      {
        "clan_id": 500154218,
        "division": 3,
        "id": 11709445,
        "claninfo": {
          "id": 11709445,
          "color": "#e3d6a0",
          "members_count": 49,
          "name": "Sea Dragon Warriors",
          "tag": "SDW",
          "disbanded": false,
          "realm": "eu",
          "hex_color": "#e3d6a0"
        },
        "players": [
          {
            "nickname": "melon101",
            "ship": {
              "level": 10,
              "name": "Alexander Nevsky"
            },
            "vehicle_id": 4074681808,
            "clan_id": 500154218,
            "survived": false,
            "result_id": 11709445,
            "name": "melon101",
            "spa_id": 518298510
          },
          {
            "nickname": "Rubber66",
            "ship": {
              "level": 10,
              "name": "Ohio"
            },
            "vehicle_id": 3760142320,
            "clan_id": 500154218,
            "survived": true,
            "result_id": 11709445,
            "name": "Rubber66",
            "spa_id": 542934383
          },
          {
            "nickname": "boomerle",
            "ship": {
              "level": 10,
              "name": "Shimakaze"
            },
            "vehicle_id": 4282267344,
            "clan_id": 500154218,
            "survived": true,
            "result_id": 11709445,
            "name": "boomerle",
            "spa_id": 500717266
          },
          {
            "nickname": "Bob_Boberson",
            "ship": {
              "level": 10,
              "name": "Moskva"
            },
            "vehicle_id": 4179539408,
            "clan_id": 500154218,
            "survived": true,
            "result_id": 11709445,
            "name": "Bob_Boberson",
            "spa_id": 566261109
          },
          {
            "nickname": "Chrissi_1984",
            "ship": {
              "level": 10,
              "name": "Montana"
            },
            "vehicle_id": 4277090288,
            "clan_id": 500154218,
            "survived": false,
            "result_id": 11709445,
            "name": "Chrissi_1984",
            "spa_id": 529106039
          },
          {
            "nickname": "Luparlif",
            "ship": {
              "level": 10,
              "name": "Stalingrad"
            },
            "vehicle_id": 3760109008,
            "clan_id": 500154218,
            "survived": false,
            "result_id": 11709445,
            "name": "Luparlif",
            "spa_id": 539602650
          },
          {
            "nickname": "V_R3znov",
            "ship": {
              "level": 10,
              "name": "Daring"
            },
            "vehicle_id": 4179507152,
            "clan_id": 500154218,
            "survived": true,
            "result_id": 11709445,
            "name": "V_R3znov",
            "spa_id": 513156831
          }
        ],
        "rating_delta": -19,
        "league": 2,
        "division_rating": 93,
        "team_number": 1,
        "stage": null,
        "result": "defeat"
      }
    ]
  },
  "20:55:05-bravo": {
    "arena_id": 5415014809968004,
    "cluster_id": 4224,
    "finished_at": "2022-03-17T20:55:05+00:00",
    "id": 5889885,
    "map": {
      "name": "Land of Fire"
    },
    "map_id": 14,
    "realm": "eu",
    "season_number": 16,
    "teams": [
      {
        "clan_id": 500202767,
        "division": 2,
        "id": 11710100,
        "claninfo": {
          "id": 11710100,
          "color": "#e3d6a0",
          "members_count": 36,
          "name": "Horde of Eccentrics",
          "tag": "H-O-E",
          "disbanded": false,
          "realm": "eu",
          "hex_color": "#e3d6a0"
        },
        "players": [
          {
            "nickname": "Phantom_1511",
            "ship": {
              "level": 10,
              "name": "Shimakaze"
            },
            "vehicle_id": 4282267344,
            "clan_id": 500202767,
            "survived": false,
            "result_id": 11710100,
            "name": "Phantom_1511",
            "spa_id": 551700897
          },
          {
            "nickname": "Yuu5Eleven",
            "ship": {
              "level": 10,
              "name": "Montana"
            },
            "vehicle_id": 4277090288,
            "clan_id": 500202767,
            "survived": false,
            "result_id": 11710100,
            "name": "Yuu5Eleven",
            "spa_id": 551905283
          },
          {
            "nickname": "PantherGraph",
            "ship": {
              "level": 10,
              "name": "Des Moines"
            },
            "vehicle_id": 4273911792,
            "clan_id": 500202767,
            "survived": false,
            "result_id": 11710100,
            "name": "PantherGraph",
            "spa_id": 527886188
          },
          {
            "nickname": "Lord_Molly",
            "ship": {
              "level": 10,
              "name": "Napoli"
            },
            "vehicle_id": 3760109296,
            "clan_id": 500202767,
            "survived": false,
            "result_id": 11710100,
            "name": "Lord_Molly",
            "spa_id": 516514685
          },
          {
            "nickname": "Shadypleb",
            "ship": {
              "level": 10,
              "name": "Småland"
            },
            "vehicle_id": 3655218480,
            "clan_id": 500202767,
            "survived": false,
            "result_id": 11710100,
            "name": "Shadypleb",
            "spa_id": 500575636
          },
          {
            "nickname": "jayceedee",
            "ship": {
              "level": 10,
              "name": "Moskva"
            },
            "vehicle_id": 4179539408,
            "clan_id": 500202767,
            "survived": false,
            "result_id": 11710100,
            "name": "jayceedee",
            "spa_id": 556002838
          },
          {
            "nickname": "_Carlo96_",
            "ship": {
              "level": 10,
              "name": "Ohio"
            },
            "vehicle_id": 3760142320,
            "clan_id": 500202767,
            "survived": false,
            "result_id": 11710100,
            "name": "_Carlo96_",
            "spa_id": 555682744
          }
        ],
        "rating_delta": -18,
        "league": 2,
        "division_rating": 96,
        "team_number": 2,
        "stage": null,
        "result": "defeat"
      },
      {
        "clan_id": 500139971,
        "division": 1,
        "id": 11710099,
        "claninfo": {
          "id": 11710099,
          "color": "#e3d6a0",
          "members_count": 33,
          "name": "Sierra Hotel Echo November",
          "tag": "SHEN",
          "disbanded": false,
          "realm": "eu",
          "hex_color": "#e3d6a0"
        },
        "players": [
          {
            "nickname": "MelKeeZ",
            "ship": {
              "level": 10,
              "name": "Somers"
            },
            "vehicle_id": 3760076784,
            "clan_id": 500139971,
            "survived": false,
            "result_id": 11710099,
            "name": "MelKeeZ",
            "spa_id": 555622440
          },
          {
            "nickname": "InoThalassa",
            "ship": {
              "level": 10,
              "name": "Des Moines"
            },
            "vehicle_id": 4273911792,
            "clan_id": 500139971,
            "survived": true,
            "result_id": 11710099,
            "name": "InoThalassa",
            "spa_id": 531098826
          },
          {
            "nickname": "Podalire",
            "ship": {
              "level": 10,
              "name": "Napoli"
            },
            "vehicle_id": 3760109296,
            "clan_id": 500139971,
            "survived": true,
            "result_id": 11710099,
            "name": "Podalire",
            "spa_id": 537494448
          },
          {
            "nickname": "rhadamanthe4",
            "ship": {
              "level": 10,
              "name": "Yamato"
            },
            "vehicle_id": 4276041424,
            "clan_id": 500139971,
            "survived": true,
            "result_id": 11710099,
            "name": "rhadamanthe4",
            "spa_id": 565721950
          },
          {
            "nickname": "Salamender85",
            "ship": {
              "level": 10,
              "name": "Småland"
            },
            "vehicle_id": 3655218480,
            "clan_id": 500139971,
            "survived": true,
            "result_id": 11710099,
            "name": "Salamender85",
            "spa_id": 541577242
          },
          {
            "nickname": "Gart786",
            "ship": {
              "level": 10,
              "name": "Kremlin"
            },
            "vehicle_id": 4179572176,
            "clan_id": 500139971,
            "survived": false,
            "result_id": 11710099,
            "name": "Gart786",
            "spa_id": 526332797
          },
          {
            "nickname": "GeoCruiser",
            "ship": {
              "level": 10,
              "name": "Ragnar"
            },
            "vehicle_id": 3550360880,
            "clan_id": 500139971,
            "survived": true,
            "result_id": 11710099,
            "name": "GeoCruiser",
            "spa_id": 534507326
          }
        ],
        "rating_delta": 19,
        "league": 2,
        "division_rating": 92,
        "team_number": 2,
        "stage": null,
        "result": "victory"
      }
    ]
  },
  "21:12:55-bravo": {
    "arena_id": 5444439630913774,
    "cluster_id": 4224,
    "finished_at": "2022-03-17T21:12:55+00:00",
    "id": 5890128,
    "map": {
      "name": "North"
    },
    "map_id": 8,
    "realm": "eu",
    "season_number": 16,
    "teams": [
      {
        "clan_id": 500202767,
        "division": 1,
        "id": 11710586,
        "claninfo": {
          "id": 11710586,
          "color": "#e3d6a0",
          "members_count": 36,
          "name": "Horde of Eccentrics",
          "tag": "H-O-E",
          "disbanded": false,
          "realm": "eu",
          "hex_color": "#e3d6a0"
        },
        "players": [
          {
            "nickname": "Phantom_1511",
            "ship": {
              "level": 10,
              "name": "Shimakaze"
            },
            "vehicle_id": 4282267344,
            "clan_id": 500202767,
            "survived": false,
            "result_id": 11710586,
            "name": "Phantom_1511",
            "spa_id": 551700897
          },
          {
            "nickname": "Yuu5Eleven",
            "ship": {
              "level": 10,
              "name": "Montana"
            },
            "vehicle_id": 4277090288,
            "clan_id": 500202767,
            "survived": false,
            "result_id": 11710586,
            "name": "Yuu5Eleven",
            "spa_id": 551905283
          },
          {
            "nickname": "PantherGraph",
            "ship": {
              "level": 10,
              "name": "Des Moines"
            },
            "vehicle_id": 4273911792,
            "clan_id": 500202767,
            "survived": false,
            "result_id": 11710586,
            "name": "PantherGraph",
            "spa_id": 527886188
          },
          {
            "nickname": "_Carlo96_",
            "ship": {
              "level": 10,
              "name": "Ohio"
            },
            "vehicle_id": 3760142320,
            "clan_id": 500202767,
            "survived": true,
            "result_id": 11710586,
            "name": "_Carlo96_",
            "spa_id": 555682744
          },
          {
            "nickname": "Shadypleb",
            "ship": {
              "level": 10,
              "name": "Småland"
            },
            "vehicle_id": 3655218480,
            "clan_id": 500202767,
            "survived": true,
            "result_id": 11710586,
            "name": "Shadypleb",
            "spa_id": 500575636
          },
          {
            "nickname": "jayceedee",
            "ship": {
              "level": 10,
              "name": "Moskva"
            },
            "vehicle_id": 4179539408,
            "clan_id": 500202767,
            "survived": false,
            "result_id": 11710586,
            "name": "jayceedee",
            "spa_id": 556002838
          },
          {
            "nickname": "Lord_Molly",
            "ship": {
              "level": 10,
              "name": "Napoli"
            },
            "vehicle_id": 3760109296,
            "clan_id": 500202767,
            "survived": true,
            "result_id": 11710586,
            "name": "Lord_Molly",
            "spa_id": 516514685
          }
        ],
        "rating_delta": 22,
        "league": 2,
        "division_rating": 18,
        "team_number": 2,
        "stage": null,
        "result": "victory"
      },
      {
        "clan_id": 500140825,
        "division": 3,
        "id": 11710585,
        "claninfo": {
          "id": 11710585,
          "color": "#e3d6a0",
          "members_count": 41,
          "name": "1er division francaise libre",
          "tag": "1-DFL",
          "disbanded": false,
          "realm": "eu",
          "hex_color": "#e3d6a0"
        },
        "players": [
          {
            "nickname": "AdrienSuffren",
            "ship": {
              "level": 10,
              "name": "Venezia"
            },
            "vehicle_id": 4179539696,
            "clan_id": 500140825,
            "survived": true,
            "result_id": 11710585,
            "name": "AdrienSuffren",
            "spa_id": 532679968
          },
          {
            "nickname": "jeremietyrex",
            "ship": {
              "level": 10,
              "name": "Grosser Kurfürst"
            },
            "vehicle_id": 4179572528,
            "clan_id": 500140825,
            "survived": false,
            "result_id": 11710585,
            "name": "jeremietyrex",
            "spa_id": 505191719
          },
          {
            "nickname": "Amiral_Arnakh",
            "ship": {
              "level": 10,
              "name": "Z-52"
            },
            "vehicle_id": 4179506992,
            "clan_id": 500140825,
            "survived": false,
            "result_id": 11710585,
            "name": "Amiral_Arnakh",
            "spa_id": 575979500
          },
          {
            "nickname": "SlenderHidden",
            "ship": {
              "level": 10,
              "name": "Marceau"
            },
            "vehicle_id": 4074649424,
            "clan_id": 500140825,
            "survived": false,
            "result_id": 11710585,
            "name": "SlenderHidden",
            "spa_id": 582733200
          },
          {
            "nickname": "blackfish152",
            "ship": {
              "level": 10,
              "name": "Des Moines"
            },
            "vehicle_id": 4273911792,
            "clan_id": 500140825,
            "survived": false,
            "result_id": 11710585,
            "name": "blackfish152",
            "spa_id": 559127607
          },
          {
            "nickname": "Jogr700",
            "ship": {
              "level": 10,
              "name": "Stalingrad"
            },
            "vehicle_id": 3760109008,
            "clan_id": 500140825,
            "survived": false,
            "result_id": 11710585,
            "name": "Jogr700",
            "spa_id": 520340152
          },
          {
            "nickname": "sardine64",
            "ship": {
              "level": 10,
              "name": "Yamato"
            },
            "vehicle_id": 4276041424,
            "clan_id": 500140825,
            "survived": false,
            "result_id": 11710585,
            "name": "sardine64",
            "spa_id": 502638139
          }
        ],
        "rating_delta": -17,
        "league": 2,
        "division_rating": 68,
        "team_number": 1,
        "stage": null,
        "result": "defeat"
      }
    ]
  },
  "21:26:45-bravo": {
    "arena_id": 6389031788323980,
    "cluster_id": 4221,
    "finished_at": "2022-03-17T21:26:45+00:00",
    "id": 5890300,
    "map": {
      "name": "Shards"
    },
    "map_id": 15,
    "realm": "eu",
    "season_number": 16,
    "teams": [
      {
        "clan_id": 500202767,
        "division": 1,
        "id": 11710930,
        "claninfo": {
          "id": 11710930,
          "color": "#e3d6a0",
          "members_count": 36,
          "name": "Horde of Eccentrics",
          "tag": "H-O-E",
          "disbanded": false,
          "realm": "eu",
          "hex_color": "#e3d6a0"
        },
        "players": [
          {
            "nickname": "Yuu5Eleven",
            "ship": {
              "level": 10,
              "name": "Montana"
            },
            "vehicle_id": 4277090288,
            "clan_id": 500202767,
            "survived": false,
            "result_id": 11710930,
            "name": "Yuu5Eleven",
            "spa_id": 551905283
          },
          {
            "nickname": "Phantom_1511",
            "ship": {
              "level": 10,
              "name": "Shimakaze"
            },
            "vehicle_id": 4282267344,
            "clan_id": 500202767,
            "survived": false,
            "result_id": 11710930,
            "name": "Phantom_1511",
            "spa_id": 551700897
          },
          {
            "nickname": "PantherGraph",
            "ship": {
              "level": 10,
              "name": "Des Moines"
            },
            "vehicle_id": 4273911792,
            "clan_id": 500202767,
            "survived": true,
            "result_id": 11710930,
            "name": "PantherGraph",
            "spa_id": 527886188
          },
          {
            "nickname": "Shadypleb",
            "ship": {
              "level": 10,
              "name": "Småland"
            },
            "vehicle_id": 3655218480,
            "clan_id": 500202767,
            "survived": true,
            "result_id": 11710930,
            "name": "Shadypleb",
            "spa_id": 500575636
          },
          {
            "nickname": "jayceedee",
            "ship": {
              "level": 10,
              "name": "Moskva"
            },
            "vehicle_id": 4179539408,
            "clan_id": 500202767,
            "survived": true,
            "result_id": 11710930,
            "name": "jayceedee",
            "spa_id": 556002838
          },
          {
            "nickname": "_Carlo96_",
            "ship": {
              "level": 10,
              "name": "Ohio"
            },
            "vehicle_id": 3760142320,
            "clan_id": 500202767,
            "survived": false,
            "result_id": 11710930,
            "name": "_Carlo96_",
            "spa_id": 555682744
          },
          {
            "nickname": "Lord_Molly",
            "ship": {
              "level": 10,
              "name": "Napoli"
            },
            "vehicle_id": 3760109296,
            "clan_id": 500202767,
            "survived": false,
            "result_id": 11710930,
            "name": "Lord_Molly",
            "spa_id": 516514685
          }
        ],
        "rating_delta": 20,
        "league": 2,
        "division_rating": 38,
        "team_number": 2,
        "stage": null,
        "result": "victory"
      },
      {
        "clan_id": 500154639,
        "division": 2,
        "id": 11710929,
        "claninfo": {
          "id": 11710929,
          "color": "#e3d6a0",
          "members_count": 45,
          "name": "TERCIO ESPAÑOL ARMADO",
          "tag": "TEAR",
          "disbanded": false,
          "realm": "eu",
          "hex_color": "#e3d6a0"
        },
        "players": [
          {
            "nickname": "Juanmib",
            "ship": {
              "level": 10,
              "name": "Napoli"
            },
            "vehicle_id": 3760109296,
            "clan_id": 500154639,
            "survived": false,
            "result_id": 11710929,
            "name": "Juanmib",
            "spa_id": 537801345
          },
          {
            "nickname": "Matanza91",
            "ship": {
              "level": 10,
              "name": "Shikishima"
            },
            "vehicle_id": 3760142032,
            "clan_id": 500154639,
            "survived": false,
            "result_id": 11710929,
            "name": "Matanza91",
            "spa_id": 527064965
          },
          {
            "nickname": "Roh_Zero",
            "ship": {
              "level": 10,
              "name": "Ragnar"
            },
            "vehicle_id": 3550360880,
            "clan_id": 500154639,
            "survived": false,
            "result_id": 11710929,
            "name": "Roh_Zero",
            "spa_id": 566509000
          },
          {
            "nickname": "jlop1975",
            "ship": {
              "level": 10,
              "name": "Moskva"
            },
            "vehicle_id": 4179539408,
            "clan_id": 500154639,
            "survived": false,
            "result_id": 11710929,
            "name": "jlop1975",
            "spa_id": 503331914
          },
          {
            "nickname": "SirGargol",
            "ship": {
              "level": 10,
              "name": "Ohio"
            },
            "vehicle_id": 3760142320,
            "clan_id": 500154639,
            "survived": false,
            "result_id": 11710929,
            "name": "SirGargol",
            "spa_id": 541948691
          },
          {
            "nickname": "_bambuce_",
            "ship": {
              "level": 10,
              "name": "Daring"
            },
            "vehicle_id": 4179507152,
            "clan_id": 500154639,
            "survived": false,
            "result_id": 11710929,
            "name": "_bambuce_",
            "spa_id": 562139735
          },
          {
            "nickname": "_Weto_",
            "ship": {
              "level": 10,
              "name": "Gouden Leeuw"
            },
            "vehicle_id": 4179539728,
            "clan_id": 500154639,
            "survived": false,
            "result_id": 11710929,
            "name": "_Weto_",
            "spa_id": 565216735
          }
        ],
        "rating_delta": -19,
        "league": 2,
        "division_rating": 67,
        "team_number": 2,
        "stage": null,
        "result": "defeat"
      }
    ]
  },
  "21:45:04-bravo": {
    "arena_id": 6450686043858936,
    "cluster_id": 4221,
    "finished_at": "2022-03-17T21:45:04+00:00",
    "id": 5890511,
    "map": {
      "name": "Islands of Ice"
    },
    "map_id": 11,
    "realm": "eu",
    "season_number": 16,
    "teams": [
      {
        "clan_id": 500202767,
        "division": 1,
        "id": 11711352,
        "claninfo": {
          "id": 11711352,
          "color": "#e3d6a0",
          "members_count": 36,
          "name": "Horde of Eccentrics",
          "tag": "H-O-E",
          "disbanded": false,
          "realm": "eu",
          "hex_color": "#e3d6a0"
        },
        "players": [
          {
            "nickname": "Yuu5Eleven",
            "ship": {
              "level": 10,
              "name": "Montana"
            },
            "vehicle_id": 4277090288,
            "clan_id": 500202767,
            "survived": false,
            "result_id": 11711352,
            "name": "Yuu5Eleven",
            "spa_id": 551905283
          },
          {
            "nickname": "Phantom_1511",
            "ship": {
              "level": 10,
              "name": "Shimakaze"
            },
            "vehicle_id": 4282267344,
            "clan_id": 500202767,
            "survived": true,
            "result_id": 11711352,
            "name": "Phantom_1511",
            "spa_id": 551700897
          },
          {
            "nickname": "PantherGraph",
            "ship": {
              "level": 10,
              "name": "Des Moines"
            },
            "vehicle_id": 4273911792,
            "clan_id": 500202767,
            "survived": true,
            "result_id": 11711352,
            "name": "PantherGraph",
            "spa_id": 527886188
          },
          {
            "nickname": "Shadypleb",
            "ship": {
              "level": 10,
              "name": "Småland"
            },
            "vehicle_id": 3655218480,
            "clan_id": 500202767,
            "survived": false,
            "result_id": 11711352,
            "name": "Shadypleb",
            "spa_id": 500575636
          },
          {
            "nickname": "jayceedee",
            "ship": {
              "level": 10,
              "name": "Moskva"
            },
            "vehicle_id": 4179539408,
            "clan_id": 500202767,
            "survived": true,
            "result_id": 11711352,
            "name": "jayceedee",
            "spa_id": 556002838
          },
          {
            "nickname": "_Carlo96_",
            "ship": {
              "level": 10,
              "name": "Ohio"
            },
            "vehicle_id": 3760142320,
            "clan_id": 500202767,
            "survived": false,
            "result_id": 11711352,
            "name": "_Carlo96_",
            "spa_id": 555682744
          },
          {
            "nickname": "Lord_Molly",
            "ship": {
              "level": 10,
              "name": "Napoli"
            },
            "vehicle_id": 3760109296,
            "clan_id": 500202767,
            "survived": false,
            "result_id": 11711352,
            "name": "Lord_Molly",
            "spa_id": 516514685
          }
        ],
        "rating_delta": 20,
        "league": 2,
        "division_rating": 58,
        "team_number": 2,
        "stage": null,
        "result": "victory"
      },
      {
        "clan_id": 500160317,
        "division": 2,
        "id": 11711351,
        "claninfo": {
          "id": 11711351,
          "color": "#e3d6a0",
          "members_count": 32,
          "name": "Shells Ablaze",
          "tag": "SA",
          "disbanded": false,
          "realm": "eu",
          "hex_color": "#e3d6a0"
        },
        "players": [
          {
            "nickname": "Commander_Anders",
            "ship": {
              "level": 10,
              "name": "Venezia"
            },
            "vehicle_id": 4179539696,
            "clan_id": 500160317,
            "survived": true,
            "result_id": 11711351,
            "name": "Commander_Anders",
            "spa_id": 519253025
          },
          {
            "nickname": "isthisteamdeadin5again",
            "ship": {
              "level": 10,
              "name": "Moskva"
            },
            "vehicle_id": 4179539408,
            "clan_id": 500160317,
            "survived": false,
            "result_id": 11711351,
            "name": "isthisteamdeadin5again",
            "spa_id": 531021508
          },
          {
            "nickname": "Sheepysean82",
            "ship": {
              "level": 10,
              "name": "Småland"
            },
            "vehicle_id": 3655218480,
            "clan_id": 500160317,
            "survived": false,
            "result_id": 11711351,
            "name": "Sheepysean82",
            "spa_id": 527592682
          },
          {
            "nickname": "CarpeDiem_2013",
            "ship": {
              "level": 10,
              "name": "Montana"
            },
            "vehicle_id": 4277090288,
            "clan_id": 500160317,
            "survived": true,
            "result_id": 11711351,
            "name": "CarpeDiem_2013",
            "spa_id": 514877266
          },
          {
            "nickname": "Cenasi",
            "ship": {
              "level": 10,
              "name": "Kremlin"
            },
            "vehicle_id": 4179572176,
            "clan_id": 500160317,
            "survived": false,
            "result_id": 11711351,
            "name": "Cenasi",
            "spa_id": 500754007
          },
          {
            "nickname": "DevilWarshipper",
            "ship": {
              "level": 10,
              "name": "Ragnar"
            },
            "vehicle_id": 3550360880,
            "clan_id": 500160317,
            "survived": false,
            "result_id": 11711351,
            "name": "DevilWarshipper",
            "spa_id": 566314329
          },
          {
            "nickname": "sanches1102",
            "ship": {
              "level": 10,
              "name": "Des Moines"
            },
            "vehicle_id": 4273911792,
            "clan_id": 500160317,
            "survived": false,
            "result_id": 11711351,
            "name": "sanches1102",
            "spa_id": 523936702
          }
        ],
        "rating_delta": -19,
        "league": 2,
        "division_rating": 56,
        "team_number": 2,
        "stage": null,
        "result": "defeat"
      }
    ]
  },
  "21:59:32-alpha": {
    "arena_id": 5155723339344930,
    "cluster_id": 4224,
    "finished_at": "2022-03-17T21:59:32+00:00",
    "id": 5890659,
    "map": {
      "name": "Crash Zone Alpha"
    },
    "map_id": 32,
    "realm": "eu",
    "season_number": 16,
    "teams": [
      {
        "league": 2,
        "stage": null,
        "result": "defeat",
        "division_rating": 66,
        "players": [
          {
            "nickname": "Yuu5Eleven",
            "result_id": 11711648,
            "spa_id": 551905283,
            "ship": {
              "level": 10,
              "name": "Montana"
            },
            "survived": false,
            "vehicle_id": 4277090288,
            "name": "Yuu5Eleven",
            "clan_id": 500202767
          },
          {
            "nickname": "PantherGraph",
            "result_id": 11711648,
            "spa_id": 527886188,
            "ship": {
              "level": 10,
              "name": "Des Moines"
            },
            "survived": true,
            "vehicle_id": 4273911792,
            "name": "PantherGraph",
            "clan_id": 500202767
          },
          {
            "nickname": "Phantom_1511",
            "result_id": 11711648,
            "spa_id": 551700897,
            "ship": {
              "level": 10,
              "name": "Shimakaze"
            },
            "survived": false,
            "vehicle_id": 4282267344,
            "name": "Phantom_1511",
            "clan_id": 500202767
          },
          {
            "nickname": "Shadypleb",
            "result_id": 11711648,
            "spa_id": 500575636,
            "ship": {
              "level": 10,
              "name": "Småland"
            },
            "survived": false,
            "vehicle_id": 3655218480,
            "name": "Shadypleb",
            "clan_id": 500202767
          },
          {
            "nickname": "jayceedee",
            "result_id": 11711648,
            "spa_id": 556002838,
            "ship": {
              "level": 10,
              "name": "Moskva"
            },
            "survived": false,
            "vehicle_id": 4179539408,
            "name": "jayceedee",
            "clan_id": 500202767
          },
          {
            "nickname": "_Carlo96_",
            "result_id": 11711648,
            "spa_id": 555682744,
            "ship": {
              "level": 10,
              "name": "Ohio"
            },
            "survived": true,
            "vehicle_id": 3760142320,
            "name": "_Carlo96_",
            "clan_id": 500202767
          },
          {
            "nickname": "Lord_Molly",
            "result_id": 11711648,
            "spa_id": 516514685,
            "ship": {
              "level": 10,
              "name": "Napoli"
            },
            "survived": false,
            "vehicle_id": 3760109296,
            "name": "Lord_Molly",
            "clan_id": 500202767
          }
        ],
        "id": 11711648,
        "rating_delta": -33,
        "team_number": 1,
        "division": 1,
        "clan_id": 500202767,
        "claninfo": {
          "tag": "H-O-E",
          "id": 11711648,
          "hex_color": "#e3d6a0",
          "realm": "eu",
          "color": "#e3d6a0",
          "name": "Horde of Eccentrics",
          "disbanded": false,
          "members_count": 36
        }
      },
      {
        "league": 1,
        "stage": null,
        "result": "victory",
        "division_rating": 74,
        "players": [
          {
            "nickname": "Dividella",
            "result_id": 11711647,
            "spa_id": 552660257,
            "ship": {
              "level": 10,
              "name": "Forrest Sherman"
            },
            "survived": true,
            "vehicle_id": 3655219184,
            "name": "Dividella",
            "clan_id": 500140489
          },
          {
            "nickname": "garstigeBratkartoffel",
            "result_id": 11711647,
            "spa_id": 557089570,
            "ship": {
              "level": 10,
              "name": "Ragnar"
            },
            "survived": true,
            "vehicle_id": 3550360880,
            "name": "garstigeBratkartoffel",
            "clan_id": 500140489
          },
          {
            "nickname": "Gr1maldus",
            "result_id": 11711647,
            "spa_id": 527749607,
            "ship": {
              "level": 10,
              "name": "Napoli"
            },
            "survived": false,
            "vehicle_id": 3760109296,
            "name": "Gr1maldus",
            "clan_id": 500140489
          },
          {
            "nickname": "WildeUschi",
            "result_id": 11711647,
            "spa_id": 504095725,
            "ship": {
              "level": 10,
              "name": "Ohio"
            },
            "survived": true,
            "vehicle_id": 3760142320,
            "name": "WildeUschi",
            "clan_id": 500140489
          },
          {
            "nickname": "Rhodanos213",
            "result_id": 11711647,
            "spa_id": 529933360,
            "ship": {
              "level": 10,
              "name": "Shimakaze"
            },
            "survived": false,
            "vehicle_id": 4282267344,
            "name": "Rhodanos213",
            "clan_id": 500140489
          },
          {
            "nickname": "Pures_Ch4os",
            "result_id": 11711647,
            "spa_id": 544742420,
            "ship": {
              "level": 10,
              "name": "Alexander Nevsky"
            },
            "survived": false,
            "vehicle_id": 4074681808,
            "name": "Pures_Ch4os",
            "clan_id": 500140489
          },
          {
            "nickname": "ROJ85",
            "result_id": 11711647,
            "spa_id": 521733628,
            "ship": {
              "level": 10,
              "name": "Kremlin"
            },
            "survived": false,
            "vehicle_id": 4179572176,
            "name": "ROJ85",
            "clan_id": 500140489
          }
        ],
        "id": 11711647,
        "rating_delta": 21,
        "team_number": 2,
        "division": 3,
        "clan_id": 500140489,
        "claninfo": {
          "tag": "UN",
          "id": 11711647,
          "hex_color": "#bee7bd",
          "realm": "eu",
          "color": "#bee7bd",
          "name": "UschiNatoren",
          "disbanded": false,
          "members_count": 39
        }
      }
    ]
  }
}
